iask/__init__.py
iask/_internal.py
iask/client.py
iask/client.pyi
iask/typing.py
iaskai-0.1.4.dist-info/licenses/LICENSE
iaskai-0.1.4.dist-info/METADATA
iaskai-0.1.4.dist-info/WHEEL
iaskai-0.1.4.dist-info/top_level.txt
iaskai-0.1.4.dist-info/RECORD
