Metadata-Version: 2.4
Name: iaskai
Version: 0.1.4
Summary: Unoffical iask.ai client
Author-email: gingdev <thanh1101dev@gmail.com>
Project-URL: Homepage, https://github.com/ging-dev/iask.ai-python
Project-URL: Issues, https://github.com/ging-dev/iask.ai-python/issues
Classifier: Programming Language :: Python :: 3
Classifier: License :: OSI Approved :: MIT License
Classifier: Operating System :: OS Independent
Requires-Python: >=3.12
License-File: LICENSE
Requires-Dist: aiohttp
Requires-Dist: lxml
Requires-Dist: markdownify
Provides-Extra: dev
Requires-Dist: build; extra == "dev"
Requires-Dist: pytest; extra == "dev"
Requires-Dist: pytest-asyncio; extra == "dev"
Requires-Dist: twine; extra == "dev"
Dynamic: license-file
